{"quote_count": 0, "contributors": null, "truncated": false, "text": "RT @MotoGP: Future faces: the 2019 #MotoGP graduates\n\nSome of the biggest names on the #Moto2 grid are already signed up for the premier cl\u2026", "is_quote_status": false, "in_reply_to_status_id": null, "reply_count": 0, "id": 1024569246431494144, "favorite_count": 0, "entities": {"user_mentions": [{"id": 14082692, "indices": [3, 10], "id_str": "14082692", "screen_name": "MotoGP", "name": "MotoGP\u2122\ud83c\udde8\ud83c\uddff\ud83c\udfc1"}], "symbols": [], "hashtags": [{"indices": [35, 42], "text": "MotoGP"}, {"indices": [87, 93], "text": "Moto2"}], "urls": []}, "retweeted": false, "coordinates": null, "timestamp_ms": "1533111318582", "source": "<a href=\"http://twitter.com/download/iphone\" rel=\"nofollow\">Twitter for iPhone</a>", "in_reply_to_screen_name": null, "id_str": "1024569246431494144", "retweet_count": 0, "in_reply_to_user_id": null, "favorited": false, "retweeted_status": {"quote_count": 0, "contributors": null, "truncated": true, "text": "Future faces: the 2019 #MotoGP graduates\n\nSome of the biggest names on the #Moto2 grid are already signed up for th\u2026 https://t.co/vXGjcxH5OZ", "is_quote_status": false, "in_reply_to_status_id": null, "reply_count": 0, "id": 1024569170065846272, "favorite_count": 3, "entities": {"user_mentions": [], "symbols": [], "hashtags": [{"indices": [23, 30], "text": "MotoGP"}, {"indices": [75, 81], "text": "Moto2"}], "urls": [{"url": "https://t.co/vXGjcxH5OZ", "indices": [117, 140], "expanded_url": "https://twitter.com/i/web/status/1024569170065846272", "display_url": "twitter.com/i/web/status/1\u2026"}]}, "retweeted": false, "coordinates": null, "source": "<a href=\"https://about.twitter.com/products/tweetdeck\" rel=\"nofollow\">TweetDeck</a>", "in_reply_to_screen_name": null, "id_str": "1024569170065846272", "display_text_range": [0, 140], "retweet_count": 2, "in_reply_to_user_id": null, "favorited": false, "user": {"follow_request_sent": null, "profile_use_background_image": true, "default_profile_image": false, "id": 14082692, "default_profile": false, "verified": true, "profile_image_url_https": "https://pbs.twimg.com/profile_images/466637052885217280/sVktQhxZ_normal.png", "profile_sidebar_fill_color": "DEDEDE", "profile_text_color": "262626", "followers_count": 2434118, "profile_sidebar_border_color": "FFFFFF", "id_str": "14082692", "profile_background_color": "000000", "listed_count": 10147, "profile_background_image_url_https": "https://abs.twimg.com/images/themes/theme1/bg.png", "utc_offset": null, "statuses_count": 50933, "description": "First on the throttle, last on the brakes.", "friends_count": 286, "location": "The World", "profile_link_color": "ED134D", "profile_image_url": "http://pbs.twimg.com/profile_images/466637052885217280/sVktQhxZ_normal.png", "following": null, "geo_enabled": false, "profile_banner_url": "https://pbs.twimg.com/profile_banners/14082692/1533038792", "profile_background_image_url": "http://abs.twimg.com/images/themes/theme1/bg.png", "name": "MotoGP\u2122\ud83c\udde8\ud83c\uddff\ud83c\udfc1", "lang": "en", "profile_background_tile": false, "favourites_count": 5992, "screen_name": "MotoGP", "notifications": null, "url": "http://www.motogp.com", "created_at": "Wed Mar 05 11:19:05 +0000 2008", "contributors_enabled": false, "time_zone": null, "protected": false, "translator_type": "none", "is_translator": false}, "geo": null, "in_reply_to_user_id_str": null, "possibly_sensitive": false, "lang": "en", "extended_tweet": {"display_text_range": [0, 218], "entities": {"user_mentions": [], "symbols": [], "hashtags": [{"indices": [23, 30], "text": "MotoGP"}, {"indices": [75, 81], "text": "Moto2"}], "urls": [{"url": "https://t.co/wt7vh8Scwk", "indices": [195, 218], "expanded_url": "http://www.motogp.com/en/news/2018/07/16/future-faces-the-2019-motogp-graduates/265890", "display_url": "motogp.com/en/news/2018/0\u2026"}], "media": [{"expanded_url": "https://twitter.com/MotoGP/status/1024569170065846272/photo/1", "display_url": "pic.twitter.com/stIDzgY4PN", "url": "https://t.co/stIDzgY4PN", "media_url_https": "https://pbs.twimg.com/media/Djf_D0fX4AA-Fhn.jpg", "id_str": "1024567881344999424", "sizes": {"large": {"h": 800, "resize": "fit", "w": 1200}, "small": {"h": 453, "resize": "fit", "w": 680}, "medium": {"h": 800, "resize": "fit", "w": 1200}, "thumb": {"h": 150, "resize": "crop", "w": 150}}, "indices": [219, 242], "type": "photo", "id": 1024567881344999424, "media_url": "http://pbs.twimg.com/media/Djf_D0fX4AA-Fhn.jpg"}]}, "extended_entities": {"media": [{"expanded_url": "https://twitter.com/MotoGP/status/1024569170065846272/photo/1", "display_url": "pic.twitter.com/stIDzgY4PN", "url": "https://t.co/stIDzgY4PN", "media_url_https": "https://pbs.twimg.com/media/Djf_D0fX4AA-Fhn.jpg", "id_str": "1024567881344999424", "sizes": {"large": {"h": 800, "resize": "fit", "w": 1200}, "small": {"h": 453, "resize": "fit", "w": 680}, "medium": {"h": 800, "resize": "fit", "w": 1200}, "thumb": {"h": 150, "resize": "crop", "w": 150}}, "indices": [219, 242], "type": "photo", "id": 1024567881344999424, "media_url": "http://pbs.twimg.com/media/Djf_D0fX4AA-Fhn.jpg"}]}, "full_text": "Future faces: the 2019 #MotoGP graduates\n\nSome of the biggest names on the #Moto2 grid are already signed up for the premier class next year. But how well do you know them?\n\nHalf-term Report | \ud83d\udcd1 https://t.co/wt7vh8Scwk https://t.co/stIDzgY4PN"}, "created_at": "Wed Aug 01 08:15:00 +0000 2018", "filter_level": "low", "in_reply_to_status_id_str": null, "place": null}, "user": {"follow_request_sent": null, "profile_use_background_image": false, "default_profile_image": false, "id": 2821625346, "default_profile": false, "verified": false, "profile_image_url_https": "https://pbs.twimg.com/profile_images/1017486694352871424/gyvinhpQ_normal.jpg", "profile_sidebar_fill_color": "000000", "profile_text_color": "000000", "followers_count": 168, "profile_sidebar_border_color": "000000", "id_str": "2821625346", "profile_background_color": "000000", "listed_count": 10, "profile_background_image_url_https": "https://abs.twimg.com/images/themes/theme1/bg.png", "utc_offset": null, "statuses_count": 15364, "description": "#Blackhawks\ud83c\udfd2\ud83e\udd45 #BrentSeabrook #7 #Ducati\ud83c\udfcd #JorgeLorenzo #JL99\ud83d\ude08 #Cubs\ud83d\udc3b\u26be\ufe0f #KrisBryant #17 Blood doesn\u2019t make U family. Loyalty does #Hockey #MotoGP #Baseball", "friends_count": 568, "location": "Hawaii  \u27a1\ufe0f Chicago", "profile_link_color": "19CF86", "profile_image_url": "http://pbs.twimg.com/profile_images/1017486694352871424/gyvinhpQ_normal.jpg", "following": null, "geo_enabled": true, "profile_banner_url": "https://pbs.twimg.com/profile_banners/2821625346/1523525923", "profile_background_image_url": "http://abs.twimg.com/images/themes/theme1/bg.png", "name": "\ud83d\ude08 Natalie \ud83d\ude07", "lang": "en", "profile_background_tile": false, "favourites_count": 4061, "screen_name": "Natalie79917", "notifications": null, "url": null, "created_at": "Sat Sep 20 11:04:12 +0000 2014", "contributors_enabled": false, "time_zone": null, "protected": false, "translator_type": "none", "is_translator": false}, "geo": null, "in_reply_to_user_id_str": null, "lang": "en", "created_at": "Wed Aug 01 08:15:18 +0000 2018", "filter_level": "low", "in_reply_to_status_id_str": null, "place": null}
{"quote_count": 0, "contributors": null, "truncated": false, "text": "RT @MotoGP: Future faces: the 2019 #MotoGP graduates\n\nSome of the biggest names on the #Moto2 grid are already signed up for the premier cl\u2026", "is_quote_status": false, "in_reply_to_status_id": null, "reply_count": 0, "id": 1024569259874078720, "favorite_count": 0, "entities": {"user_mentions": [{"id": 14082692, "indices": [3, 10], "id_str": "14082692", "screen_name": "MotoGP", "name": "MotoGP\u2122\ud83c\udde8\ud83c\uddff\ud83c\udfc1"}], "symbols": [], "hashtags": [{"indices": [35, 42], "text": "MotoGP"}, {"indices": [87, 93], "text": "Moto2"}], "urls": []}, "retweeted": false, "coordinates": null, "timestamp_ms": "1533111321787", "source": "<a href=\"https://about.twitter.com/products/tweetdeck\" rel=\"nofollow\">TweetDeck</a>", "in_reply_to_screen_name": null, "id_str": "1024569259874078720", "retweet_count": 0, "in_reply_to_user_id": null, "favorited": false, "retweeted_status": {"quote_count": 0, "contributors": null, "truncated": true, "text": "Future faces: the 2019 #MotoGP graduates\n\nSome of the biggest names on the #Moto2 grid are already signed up for th\u2026 https://t.co/vXGjcxH5OZ", "is_quote_status": false, "in_reply_to_status_id": null, "reply_count": 0, "id": 1024569170065846272, "favorite_count": 4, "entities": {"user_mentions": [], "symbols": [], "hashtags": [{"indices": [23, 30], "text": "MotoGP"}, {"indices": [75, 81], "text": "Moto2"}], "urls": [{"url": "https://t.co/vXGjcxH5OZ", "indices": [117, 140], "expanded_url": "https://twitter.com/i/web/status/1024569170065846272", "display_url": "twitter.com/i/web/status/1\u2026"}]}, "retweeted": false, "coordinates": null, "source": "<a href=\"https://about.twitter.com/products/tweetdeck\" rel=\"nofollow\">TweetDeck</a>", "in_reply_to_screen_name": null, "id_str": "1024569170065846272", "display_text_range": [0, 140], "retweet_count": 3, "in_reply_to_user_id": null, "favorited": false, "user": {"follow_request_sent": null, "profile_use_background_image": true, "default_profile_image": false, "id": 14082692, "default_profile": false, "verified": true, "profile_image_url_https": "https://pbs.twimg.com/profile_images/466637052885217280/sVktQhxZ_normal.png", "profile_sidebar_fill_color": "DEDEDE", "profile_text_color": "262626", "followers_count": 2434101, "profile_sidebar_border_color": "FFFFFF", "id_str": "14082692", "profile_background_color": "000000", "listed_count": 10137, "profile_background_image_url_https": "https://abs.twimg.com/images/themes/theme1/bg.png", "utc_offset": null, "statuses_count": 50933, "description": "First on the throttle, last on the brakes.", "friends_count": 286, "location": "The World", "profile_link_color": "ED134D", "profile_image_url": "http://pbs.twimg.com/profile_images/466637052885217280/sVktQhxZ_normal.png", "following": null, "geo_enabled": false, "profile_banner_url": "https://pbs.twimg.com/profile_banners/14082692/1533038792", "profile_background_image_url": "http://abs.twimg.com/images/themes/theme1/bg.png", "name": "MotoGP\u2122\ud83c\udde8\ud83c\uddff\ud83c\udfc1", "lang": "en", "profile_background_tile": false, "favourites_count": 5992, "screen_name": "MotoGP", "notifications": null, "url": "http://www.motogp.com", "created_at": "Wed Mar 05 11:19:05 +0000 2008", "contributors_enabled": false, "time_zone": null, "protected": false, "translator_type": "none", "is_translator": false}, "geo": null, "in_reply_to_user_id_str": null, "possibly_sensitive": false, "lang": "en", "extended_tweet": {"display_text_range": [0, 218], "entities": {"user_mentions": [], "symbols": [], "hashtags": [{"indices": [23, 30], "text": "MotoGP"}, {"indices": [75, 81], "text": "Moto2"}], "urls": [{"url": "https://t.co/wt7vh8Scwk", "indices": [195, 218], "expanded_url": "http://www.motogp.com/en/news/2018/07/16/future-faces-the-2019-motogp-graduates/265890", "display_url": "motogp.com/en/news/2018/0\u2026"}], "media": [{"expanded_url": "https://twitter.com/MotoGP/status/1024569170065846272/photo/1", "display_url": "pic.twitter.com/stIDzgY4PN", "url": "https://t.co/stIDzgY4PN", "media_url_https": "https://pbs.twimg.com/media/Djf_D0fX4AA-Fhn.jpg", "id_str": "1024567881344999424", "sizes": {"large": {"h": 800, "resize": "fit", "w": 1200}, "small": {"h": 453, "resize": "fit", "w": 680}, "medium": {"h": 800, "resize": "fit", "w": 1200}, "thumb": {"h": 150, "resize": "crop", "w": 150}}, "indices": [219, 242], "type": "photo", "id": 1024567881344999424, "media_url": "http://pbs.twimg.com/media/Djf_D0fX4AA-Fhn.jpg"}]}, "extended_entities": {"media": [{"expanded_url": "https://twitter.com/MotoGP/status/1024569170065846272/photo/1", "display_url": "pic.twitter.com/stIDzgY4PN", "url": "https://t.co/stIDzgY4PN", "media_url_https": "https://pbs.twimg.com/media/Djf_D0fX4AA-Fhn.jpg", "id_str": "1024567881344999424", "sizes": {"large": {"h": 800, "resize": "fit", "w": 1200}, "small": {"h": 453, "resize": "fit", "w": 680}, "medium": {"h": 800, "resize": "fit", "w": 1200}, "thumb": {"h": 150, "resize": "crop", "w": 150}}, "indices": [219, 242], "type": "photo", "id": 1024567881344999424, "media_url": "http://pbs.twimg.com/media/Djf_D0fX4AA-Fhn.jpg"}]}, "full_text": "Future faces: the 2019 #MotoGP graduates\n\nSome of the biggest names on the #Moto2 grid are already signed up for the premier class next year. But how well do you know them?\n\nHalf-term Report | \ud83d\udcd1 https://t.co/wt7vh8Scwk https://t.co/stIDzgY4PN"}, "created_at": "Wed Aug 01 08:15:00 +0000 2018", "filter_level": "low", "in_reply_to_status_id_str": null, "place": null}, "user": {"follow_request_sent": null, "profile_use_background_image": true, "default_profile_image": false, "id": 242221549, "default_profile": false, "verified": false, "profile_image_url_https": "https://pbs.twimg.com/profile_images/996224110194671616/fxQh_oeM_normal.jpg", "profile_sidebar_fill_color": "F5F5F5", "profile_text_color": "0CF054", "followers_count": 1070, "profile_sidebar_border_color": "FFFFFF", "id_str": "242221549", "profile_background_color": "F7F9FA", "listed_count": 107, "profile_background_image_url_https": "https://abs.twimg.com/images/themes/theme1/bg.png", "utc_offset": null, "statuses_count": 111878, "description": "Merseyside is Red.", "friends_count": 1878, "location": "Batam, Indonesia", "profile_link_color": "FA1905", "profile_image_url": "http://pbs.twimg.com/profile_images/996224110194671616/fxQh_oeM_normal.jpg", "following": null, "geo_enabled": true, "profile_banner_url": "https://pbs.twimg.com/profile_banners/242221549/1524977212", "profile_background_image_url": "http://abs.twimg.com/images/themes/theme1/bg.png", "name": "Renaldi Ramadhan", "lang": "en", "profile_background_tile": false, "favourites_count": 526, "screen_name": "renaldirey77", "notifications": null, "url": null, "created_at": "Mon Jan 24 07:23:20 +0000 2011", "contributors_enabled": false, "time_zone": null, "protected": false, "translator_type": "none", "is_translator": false}, "geo": null, "in_reply_to_user_id_str": null, "lang": "en", "created_at": "Wed Aug 01 08:15:21 +0000 2018", "filter_level": "low", "in_reply_to_status_id_str": null, "place": null}
{"quote_count": 0, "contributors": null, "truncated": true, "text": "#steadyGum is spreading! :) It has arrived to our colleagues from @RTVDrenthe in the Netherlands. Here, at the\u2026 https://t.co/yeTE2hdeHk", "is_quote_status": false, "in_reply_to_status_id": null, "reply_count": 0, "id": 1024569264068587520, "favorite_count": 0, "entities": {"user_mentions": [{"id": 21074905, "indices": [66, 77], "id_str": "21074905", "screen_name": "RTVDrenthe", "name": "RTV Drenthe"}], "symbols": [], "hashtags": [{"indices": [0, 10], "text": "steadyGum"}], "urls": [{"url": "https://t.co/yeTE2hdeHk", "indices": [112, 135], "expanded_url": "https://twitter.com/i/web/status/1024569264068587520", "display_url": "twitter.com/i/web/status/1\u2026"}]}, "retweeted": false, "coordinates": null, "timestamp_ms": "1533111322787", "source": "<a href=\"http://twitter.com\" rel=\"nofollow\">Twitter Web Client</a>", "in_reply_to_screen_name": null, "id_str": "1024569264068587520", "display_text_range": [0, 140], "retweet_count": 0, "in_reply_to_user_id": null, "favorited": false, "user": {"follow_request_sent": null, "profile_use_background_image": true, "default_profile_image": false, "id": 795304106990718976, "default_profile": true, "verified": false, "profile_image_url_https": "https://pbs.twimg.com/profile_images/795422797145210880/OcQwkQet_normal.jpg", "profile_sidebar_fill_color": "DDEEF6", "profile_text_color": "333333", "followers_count": 35, "profile_sidebar_border_color": "C0DEED", "id_str": "795304106990718976", "profile_background_color": "F5F8FA", "listed_count": 0, "profile_background_image_url_https": "", "utc_offset": null, "statuses_count": 39, "description": null, "friends_count": 381, "location": null, "profile_link_color": "1DA1F2", "profile_image_url": "http://pbs.twimg.com/profile_images/795422797145210880/OcQwkQet_normal.jpg", "following": null, "geo_enabled": false, "profile_banner_url": "https://pbs.twimg.com/profile_banners/795304106990718976/1478451321", "profile_background_image_url": "", "name": "steadygum", "lang": "es", "profile_background_tile": false, "favourites_count": 11, "screen_name": "steadygum", "notifications": null, "url": "http://www.steadygum.com", "created_at": "Sun Nov 06 16:37:29 +0000 2016", "contributors_enabled": false, "time_zone": null, "protected": false, "translator_type": "none", "is_translator": false}, "geo": null, "in_reply_to_user_id_str": null, "possibly_sensitive": false, "lang": "en", "extended_tweet": {"display_text_range": [0, 171], "entities": {"user_mentions": [{"id": 21074905, "indices": [66, 77], "id_str": "21074905", "screen_name": "RTVDrenthe", "name": "RTV Drenthe"}], "symbols": [], "hashtags": [{"indices": [0, 10], "text": "steadyGum"}, {"indices": [111, 118], "text": "motogp"}, {"indices": [133, 143], "text": "Cameraman"}], "urls": [], "media": [{"expanded_url": "https://twitter.com/steadygum/status/1024569264068587520/photo/1", "display_url": "pic.twitter.com/P1OgZ2yDjT", "url": "https://t.co/P1OgZ2yDjT", "media_url_https": "https://pbs.twimg.com/media/Djf8_8-W4AEFgIS.jpg", "id_str": "1024565615879708673", "sizes": {"large": {"h": 1299, "resize": "fit", "w": 996}, "small": {"h": 680, "resize": "fit", "w": 521}, "medium": {"h": 1200, "resize": "fit", "w": 920}, "thumb": {"h": 150, "resize": "crop", "w": 150}}, "indices": [172, 195], "type": "photo", "id": 1024565615879708673, "media_url": "http://pbs.twimg.com/media/Djf8_8-W4AEFgIS.jpg"}, {"expanded_url": "https://twitter.com/steadygum/status/1024569264068587520/photo/1", "display_url": "pic.twitter.com/P1OgZ2yDjT", "url": "https://t.co/P1OgZ2yDjT", "media_url_https": "https://pbs.twimg.com/media/Djf8_84X0AAg5iU.jpg", "id_str": "1024565615854604288", "sizes": {"small": {"h": 383, "resize": "fit", "w": 680}, "large": {"h": 540, "resize": "fit", "w": 960}, "medium": {"h": 540, "resize": "fit", "w": 960}, "thumb": {"h": 150, "resize": "crop", "w": 150}}, "indices": [172, 195], "type": "photo", "id": 1024565615854604288, "media_url": "http://pbs.twimg.com/media/Djf8_84X0AAg5iU.jpg"}]}, "extended_entities": {"media": [{"expanded_url": "https://twitter.com/steadygum/status/1024569264068587520/photo/1", "display_url": "pic.twitter.com/P1OgZ2yDjT", "url": "https://t.co/P1OgZ2yDjT", "media_url_https": "https://pbs.twimg.com/media/Djf8_8-W4AEFgIS.jpg", "id_str": "1024565615879708673", "sizes": {"large": {"h": 1299, "resize": "fit", "w": 996}, "small": {"h": 680, "resize": "fit", "w": 521}, "medium": {"h": 1200, "resize": "fit", "w": 920}, "thumb": {"h": 150, "resize": "crop", "w": 150}}, "indices": [172, 195], "type": "photo", "id": 1024565615879708673, "media_url": "http://pbs.twimg.com/media/Djf8_8-W4AEFgIS.jpg"}, {"expanded_url": "https://twitter.com/steadygum/status/1024569264068587520/photo/1", "display_url": "pic.twitter.com/P1OgZ2yDjT", "url": "https://t.co/P1OgZ2yDjT", "media_url_https": "https://pbs.twimg.com/media/Djf8_84X0AAg5iU.jpg", "id_str": "1024565615854604288", "sizes": {"small": {"h": 383, "resize": "fit", "w": 680}, "large": {"h": 540, "resize": "fit", "w": 960}, "medium": {"h": 540, "resize": "fit", "w": 960}, "thumb": {"h": 150, "resize": "crop", "w": 150}}, "indices": [172, 195], "type": "photo", "id": 1024565615854604288, "media_url": "http://pbs.twimg.com/media/Djf8_84X0AAg5iU.jpg"}]}, "full_text": "#steadyGum is spreading! :) It has arrived to our colleagues from @RTVDrenthe in the Netherlands. Here, at the #motogp TT in Assen. \n#Cameraman means steadyGum. Thank you! https://t.co/P1OgZ2yDjT"}, "created_at": "Wed Aug 01 08:15:22 +0000 2018", "filter_level": "low", "in_reply_to_status_id_str": null, "place": null}
{"quote_count": 0, "contributors": null, "truncated": false, "text": "RT @MotoGP: Future faces: the 2019 #MotoGP graduates\n\nSome of the biggest names on the #Moto2 grid are already signed up for the premier cl\u2026", "is_quote_status": false, "in_reply_to_status_id": null, "reply_count": 0, "id": 1024569295643262976, "favorite_count": 0, "entities": {"user_mentions": [{"id": 14082692, "indices": [3, 10], "id_str": "14082692", "screen_name": "MotoGP", "name": "MotoGP\u2122\ud83c\udde8\ud83c\uddff\ud83c\udfc1"}], "symbols": [], "hashtags": [{"indices": [35, 42], "text": "MotoGP"}, {"indices": [87, 93], "text": "Moto2"}], "urls": []}, "retweeted": false, "coordinates": null, "timestamp_ms": "1533111330315", "source": "<a href=\"http://twitter.com/download/iphone\" rel=\"nofollow\">Twitter for iPhone</a>", "in_reply_to_screen_name": null, "id_str": "1024569295643262976", "retweet_count": 0, "in_reply_to_user_id": null, "favorited": false, "retweeted_status": {"quote_count": 0, "contributors": null, "truncated": true, "text": "Future faces: the 2019 #MotoGP graduates\n\nSome of the biggest names on the #Moto2 grid are already signed up for th\u2026 https://t.co/vXGjcxH5OZ", "is_quote_status": false, "in_reply_to_status_id": null, "reply_count": 0, "id": 1024569170065846272, "favorite_count": 5, "entities": {"user_mentions": [], "symbols": [], "hashtags": [{"indices": [23, 30], "text": "MotoGP"}, {"indices": [75, 81], "text": "Moto2"}], "urls": [{"url": "https://t.co/vXGjcxH5OZ", "indices": [117, 140], "expanded_url": "https://twitter.com/i/web/status/1024569170065846272", "display_url": "twitter.com/i/web/status/1\u2026"}]}, "retweeted": false, "coordinates": null, "source": "<a href=\"https://about.twitter.com/products/tweetdeck\" rel=\"nofollow\">TweetDeck</a>", "in_reply_to_screen_name": null, "id_str": "1024569170065846272", "display_text_range": [0, 140], "retweet_count": 4, "in_reply_to_user_id": null, "favorited": false, "user": {"follow_request_sent": null, "profile_use_background_image": true, "default_profile_image": false, "id": 14082692, "default_profile": false, "verified": true, "profile_image_url_https": "https://pbs.twimg.com/profile_images/466637052885217280/sVktQhxZ_normal.png", "profile_sidebar_fill_color": "DEDEDE", "profile_text_color": "262626", "followers_count": 2434118, "profile_sidebar_border_color": "FFFFFF", "id_str": "14082692", "profile_background_color": "000000", "listed_count": 10147, "profile_background_image_url_https": "https://abs.twimg.com/images/themes/theme1/bg.png", "utc_offset": null, "statuses_count": 50933, "description": "First on the throttle, last on the brakes.", "friends_count": 286, "location": "The World", "profile_link_color": "ED134D", "profile_image_url": "http://pbs.twimg.com/profile_images/466637052885217280/sVktQhxZ_normal.png", "following": null, "geo_enabled": false, "profile_banner_url": "https://pbs.twimg.com/profile_banners/14082692/1533038792", "profile_background_image_url": "http://abs.twimg.com/images/themes/theme1/bg.png", "name": "MotoGP\u2122\ud83c\udde8\ud83c\uddff\ud83c\udfc1", "lang": "en", "profile_background_tile": false, "favourites_count": 5992, "screen_name": "MotoGP", "notifications": null, "url": "http://www.motogp.com", "created_at": "Wed Mar 05 11:19:05 +0000 2008", "contributors_enabled": false, "time_zone": null, "protected": false, "translator_type": "none", "is_translator": false}, "geo": null, "in_reply_to_user_id_str": null, "possibly_sensitive": false, "lang": "en", "extended_tweet": {"display_text_range": [0, 218], "entities": {"user_mentions": [], "symbols": [], "hashtags": [{"indices": [23, 30], "text": "MotoGP"}, {"indices": [75, 81], "text": "Moto2"}], "urls": [{"url": "https://t.co/wt7vh8Scwk", "indices": [195, 218], "expanded_url": "http://www.motogp.com/en/news/2018/07/16/future-faces-the-2019-motogp-graduates/265890", "display_url": "motogp.com/en/news/2018/0\u2026"}], "media": [{"expanded_url": "https://twitter.com/MotoGP/status/1024569170065846272/photo/1", "display_url": "pic.twitter.com/stIDzgY4PN", "url": "https://t.co/stIDzgY4PN", "media_url_https": "https://pbs.twimg.com/media/Djf_D0fX4AA-Fhn.jpg", "id_str": "1024567881344999424", "sizes": {"large": {"h": 800, "resize": "fit", "w": 1200}, "small": {"h": 453, "resize": "fit", "w": 680}, "medium": {"h": 800, "resize": "fit", "w": 1200}, "thumb": {"h": 150, "resize": "crop", "w": 150}}, "indices": [219, 242], "type": "photo", "id": 1024567881344999424, "media_url": "http://pbs.twimg.com/media/Djf_D0fX4AA-Fhn.jpg"}]}, "extended_entities": {"media": [{"expanded_url": "https://twitter.com/MotoGP/status/1024569170065846272/photo/1", "display_url": "pic.twitter.com/stIDzgY4PN", "url": "https://t.co/stIDzgY4PN", "media_url_https": "https://pbs.twimg.com/media/Djf_D0fX4AA-Fhn.jpg", "id_str": "1024567881344999424", "sizes": {"large": {"h": 800, "resize": "fit", "w": 1200}, "small": {"h": 453, "resize": "fit", "w": 680}, "medium": {"h": 800, "resize": "fit", "w": 1200}, "thumb": {"h": 150, "resize": "crop", "w": 150}}, "indices": [219, 242], "type": "photo", "id": 1024567881344999424, "media_url": "http://pbs.twimg.com/media/Djf_D0fX4AA-Fhn.jpg"}]}, "full_text": "Future faces: the 2019 #MotoGP graduates\n\nSome of the biggest names on the #Moto2 grid are already signed up for the premier class next year. But how well do you know them?\n\nHalf-term Report | \ud83d\udcd1 https://t.co/wt7vh8Scwk https://t.co/stIDzgY4PN"}, "created_at": "Wed Aug 01 08:15:00 +0000 2018", "filter_level": "low", "in_reply_to_status_id_str": null, "place": null}, "user": {"follow_request_sent": null, "profile_use_background_image": true, "default_profile_image": false, "id": 862527888771428352, "default_profile": true, "verified": false, "profile_image_url_https": "https://pbs.twimg.com/profile_images/889232933499924480/FGlg3wuJ_normal.jpg", "profile_sidebar_fill_color": "DDEEF6", "profile_text_color": "333333", "followers_count": 50, "profile_sidebar_border_color": "C0DEED", "id_str": "862527888771428352", "profile_background_color": "F5F8FA", "listed_count": 1, "profile_background_image_url_https": "", "utc_offset": null, "statuses_count": 6736, "description": "Life's roughest storms prove the strength of our anchors. #SVU #Blackhawks #Cubs @javy23baez @JonathanToews @thisisnick_09 #MM93", "friends_count": 144, "location": "Illinois, USA", "profile_link_color": "1DA1F2", "profile_image_url": "http://pbs.twimg.com/profile_images/889232933499924480/FGlg3wuJ_normal.jpg", "following": null, "geo_enabled": true, "profile_banner_url": "https://pbs.twimg.com/profile_banners/862527888771428352/1494481104", "profile_background_image_url": "", "name": "\ud83d\udc32Ashley\u2649\ufe0f", "lang": "en", "profile_background_tile": false, "favourites_count": 692, "screen_name": "cubbiehawk919", "notifications": null, "url": null, "created_at": "Thu May 11 04:40:48 +0000 2017", "contributors_enabled": false, "time_zone": null, "protected": false, "translator_type": "none", "is_translator": false}, "geo": null, "in_reply_to_user_id_str": null, "lang": "en", "created_at": "Wed Aug 01 08:15:30 +0000 2018", "filter_level": "low", "in_reply_to_status_id_str": null, "place": null}
{"quote_count": 0, "contributors": null, "truncated": false, "text": "RT @MotoGP: Future faces: the 2019 #MotoGP graduates\n\nSome of the biggest names on the #Moto2 grid are already signed up for the premier cl\u2026", "is_quote_status": false, "in_reply_to_status_id": null, "reply_count": 0, "id": 1024569316404948993, "favorite_count": 0, "entities": {"user_mentions": [{"id": 14082692, "indices": [3, 10], "id_str": "14082692", "screen_name": "MotoGP", "name": "MotoGP\u2122\ud83c\udde8\ud83c\uddff\ud83c\udfc1"}], "symbols": [], "hashtags": [{"indices": [35, 42], "text": "MotoGP"}, {"indices": [87, 93], "text": "Moto2"}], "urls": []}, "retweeted": false, "coordinates": null, "timestamp_ms": "1533111335265", "source": "<a href=\"http://twitter.com/download/android\" rel=\"nofollow\">Twitter for Android</a>", "in_reply_to_screen_name": null, "id_str": "1024569316404948993", "retweet_count": 0, "in_reply_to_user_id": null, "favorited": false, "retweeted_status": {"quote_count": 0, "contributors": null, "truncated": true, "text": "Future faces: the 2019 #MotoGP graduates\n\nSome of the biggest names on the #Moto2 grid are already signed up for th\u2026 https://t.co/vXGjcxH5OZ", "is_quote_status": false, "in_reply_to_status_id": null, "reply_count": 0, "id": 1024569170065846272, "favorite_count": 7, "entities": {"user_mentions": [], "symbols": [], "hashtags": [{"indices": [23, 30], "text": "MotoGP"}, {"indices": [75, 81], "text": "Moto2"}], "urls": [{"url": "https://t.co/vXGjcxH5OZ", "indices": [117, 140], "expanded_url": "https://twitter.com/i/web/status/1024569170065846272", "display_url": "twitter.com/i/web/status/1\u2026"}]}, "retweeted": false, "coordinates": null, "source": "<a href=\"https://about.twitter.com/products/tweetdeck\" rel=\"nofollow\">TweetDeck</a>", "in_reply_to_screen_name": null, "id_str": "1024569170065846272", "display_text_range": [0, 140], "retweet_count": 5, "in_reply_to_user_id": null, "favorited": false, "user": {"follow_request_sent": null, "profile_use_background_image": true, "default_profile_image": false, "id": 14082692, "default_profile": false, "verified": true, "profile_image_url_https": "https://pbs.twimg.com/profile_images/466637052885217280/sVktQhxZ_normal.png", "profile_sidebar_fill_color": "DEDEDE", "profile_text_color": "262626", "followers_count": 2434101, "profile_sidebar_border_color": "FFFFFF", "id_str": "14082692", "profile_background_color": "000000", "listed_count": 10137, "profile_background_image_url_https": "https://abs.twimg.com/images/themes/theme1/bg.png", "utc_offset": null, "statuses_count": 50933, "description": "First on the throttle, last on the brakes.", "friends_count": 286, "location": "The World", "profile_link_color": "ED134D", "profile_image_url": "http://pbs.twimg.com/profile_images/466637052885217280/sVktQhxZ_normal.png", "following": null, "geo_enabled": false, "profile_banner_url": "https://pbs.twimg.com/profile_banners/14082692/1533038792", "profile_background_image_url": "http://abs.twimg.com/images/themes/theme1/bg.png", "name": "MotoGP\u2122\ud83c\udde8\ud83c\uddff\ud83c\udfc1", "lang": "en", "profile_background_tile": false, "favourites_count": 5992, "screen_name": "MotoGP", "notifications": null, "url": "http://www.motogp.com", "created_at": "Wed Mar 05 11:19:05 +0000 2008", "contributors_enabled": false, "time_zone": null, "protected": false, "translator_type": "none", "is_translator": false}, "geo": null, "in_reply_to_user_id_str": null, "possibly_sensitive": false, "lang": "en", "extended_tweet": {"display_text_range": [0, 218], "entities": {"user_mentions": [], "symbols": [], "hashtags": [{"indices": [23, 30], "text": "MotoGP"}, {"indices": [75, 81], "text": "Moto2"}], "urls": [{"url": "https://t.co/wt7vh8Scwk", "indices": [195, 218], "expanded_url": "http://www.motogp.com/en/news/2018/07/16/future-faces-the-2019-motogp-graduates/265890", "display_url": "motogp.com/en/news/2018/0\u2026"}], "media": [{"expanded_url": "https://twitter.com/MotoGP/status/1024569170065846272/photo/1", "display_url": "pic.twitter.com/stIDzgY4PN", "url": "https://t.co/stIDzgY4PN", "media_url_https": "https://pbs.twimg.com/media/Djf_D0fX4AA-Fhn.jpg", "id_str": "1024567881344999424", "sizes": {"large": {"h": 800, "resize": "fit", "w": 1200}, "small": {"h": 453, "resize": "fit", "w": 680}, "medium": {"h": 800, "resize": "fit", "w": 1200}, "thumb": {"h": 150, "resize": "crop", "w": 150}}, "indices": [219, 242], "type": "photo", "id": 1024567881344999424, "media_url": "http://pbs.twimg.com/media/Djf_D0fX4AA-Fhn.jpg"}]}, "extended_entities": {"media": [{"expanded_url": "https://twitter.com/MotoGP/status/1024569170065846272/photo/1", "display_url": "pic.twitter.com/stIDzgY4PN", "url": "https://t.co/stIDzgY4PN", "media_url_https": "https://pbs.twimg.com/media/Djf_D0fX4AA-Fhn.jpg", "id_str": "1024567881344999424", "sizes": {"large": {"h": 800, "resize": "fit", "w": 1200}, "small": {"h": 453, "resize": "fit", "w": 680}, "medium": {"h": 800, "resize": "fit", "w": 1200}, "thumb": {"h": 150, "resize": "crop", "w": 150}}, "indices": [219, 242], "type": "photo", "id": 1024567881344999424, "media_url": "http://pbs.twimg.com/media/Djf_D0fX4AA-Fhn.jpg"}]}, "full_text": "Future faces: the 2019 #MotoGP graduates\n\nSome of the biggest names on the #Moto2 grid are already signed up for the premier class next year. But how well do you know them?\n\nHalf-term Report | \ud83d\udcd1 https://t.co/wt7vh8Scwk https://t.co/stIDzgY4PN"}, "created_at": "Wed Aug 01 08:15:00 +0000 2018", "filter_level": "low", "in_reply_to_status_id_str": null, "place": null}, "user": {"follow_request_sent": null, "profile_use_background_image": true, "default_profile_image": false, "id": 857217116533014529, "default_profile": true, "verified": false, "profile_image_url_https": "https://pbs.twimg.com/profile_images/1016339460361838592/PUE8H0Gh_normal.jpg", "profile_sidebar_fill_color": "DDEEF6", "profile_text_color": "333333", "followers_count": 827, "profile_sidebar_border_color": "C0DEED", "id_str": "857217116533014529", "profile_background_color": "F5F8FA", "listed_count": 10, "profile_background_image_url_https": "", "utc_offset": null, "statuses_count": 7663, "description": "\u30ac\u30eb\u30d1\u30a8\u30f3\u30b8\u30e7\u30a4\u52e2\u30e9\u30f3\u30af120\u2191\u63a8\u3057\u306f\u9999\u6f84\u3001\u6c99\u7dbe\u3001\u6709\u54b2\u3067\u3059(*\u00b4\u03c9`*)\n\n\u305d\u306e\u4ed6\u77e5\u308a\u305f\u3044\u60c5\u5831\u304c\u3042\u308b\u5834\u5408\u306f\u305c\u3072\u8cea\u554f\u3057\u3066\u304f\u3060\u3055\u3044d('\u2200'*)\n\u9999\u6f84\u63a8\u3057\u968aNo.97\n\nSCC\u6240\u5c5e\uff01\n\n\u4eba\u5dee\u3057\u6307\u7df4\u7fd2\u59cb\u3081\u307e\u3057\u305f", "friends_count": 1229, "location": null, "profile_link_color": "1DA1F2", "profile_image_url": "http://pbs.twimg.com/profile_images/1016339460361838592/PUE8H0Gh_normal.jpg", "following": null, "geo_enabled": false, "profile_banner_url": "https://pbs.twimg.com/profile_banners/857217116533014529/1533039570", "profile_background_image_url": "", "name": "Re:kurosu", "lang": "ja", "profile_background_tile": false, "favourites_count": 19426, "screen_name": "Rekurosu", "notifications": null, "url": null, "created_at": "Wed Apr 26 12:57:41 +0000 2017", "contributors_enabled": false, "time_zone": null, "protected": false, "translator_type": "none", "is_translator": false}, "geo": null, "in_reply_to_user_id_str": null, "lang": "en", "created_at": "Wed Aug 01 08:15:35 +0000 2018", "filter_level": "low", "in_reply_to_status_id_str": null, "place": null}
{"quote_count": 0, "contributors": null, "truncated": false, "text": "RT @box_repsol: #MM93 #CzechGP\n2011 \ud83d\udc49 \ud83e\udd48+ Pole #Moto2\n2012 \ud83d\udc49 \ud83c\udfc6\n2013 \ud83d\udc49 \ud83c\udfc6 + VR / FL #MotoGP\n2014 \ud83d\udc49 Pole\n2015 \ud83d\udc49 \ud83e\udd48 + VR/FL\n2016 \ud83d\udc49 \ud83e\udd49+ Pole\n2017 \ud83d\udc49\u2026", "is_quote_status": false, "in_reply_to_status_id": null, "reply_count": 0, "id": 1024569335040237569, "favorite_count": 0, "entities": {"user_mentions": [{"id": 45522363, "indices": [3, 14], "id_str": "45522363", "screen_name": "box_repsol", "name": "Box_Repsol"}], "symbols": [], "hashtags": [{"indices": [16, 21], "text": "MM93"}, {"indices": [22, 30], "text": "CzechGP"}, {"indices": [46, 52], "text": "Moto2"}, {"indices": [81, 88], "text": "MotoGP"}], "urls": []}, "retweeted": false, "coordinates": null, "timestamp_ms": "1533111339708", "source": "<a href=\"http://twitter.com\" rel=\"nofollow\">Twitter Web Client</a>", "in_reply_to_screen_name": null, "id_str": "1024569335040237569", "retweet_count": 0, "in_reply_to_user_id": null, "favorited": false, "retweeted_status": {"quote_count": 0, "contributors": null, "truncated": true, "text": "#MM93 #CzechGP\n2011 \ud83d\udc49 \ud83e\udd48+ Pole #Moto2\n2012 \ud83d\udc49 \ud83c\udfc6\n2013 \ud83d\udc49 \ud83c\udfc6 + VR / FL #MotoGP\n2014 \ud83d\udc49 Pole\n2015 \ud83d\udc49 \ud83e\udd48 + VR/FL\n2016 \ud83d\udc49 \ud83e\udd49+ Pol\u2026 https://t.co/iaG3WkTYdn", "is_quote_status": false, "in_reply_to_status_id": null, "reply_count": 0, "id": 1024567741813010432, "favorite_count": 10, "entities": {"user_mentions": [], "symbols": [], "hashtags": [{"indices": [0, 5], "text": "MM93"}, {"indices": [6, 14], "text": "CzechGP"}, {"indices": [30, 36], "text": "Moto2"}, {"indices": [65, 72], "text": "MotoGP"}], "urls": [{"url": "https://t.co/iaG3WkTYdn", "indices": [117, 140], "expanded_url": "https://twitter.com/i/web/status/1024567741813010432", "display_url": "twitter.com/i/web/status/1\u2026"}]}, "retweeted": false, "coordinates": null, "source": "<a href=\"http://twitter.com\" rel=\"nofollow\">Twitter Web Client</a>", "in_reply_to_screen_name": null, "id_str": "1024567741813010432", "display_text_range": [0, 140], "retweet_count": 6, "in_reply_to_user_id": null, "favorited": false, "user": {"follow_request_sent": null, "profile_use_background_image": true, "default_profile_image": false, "id": 45522363, "default_profile": false, "verified": true, "profile_image_url_https": "https://pbs.twimg.com/profile_images/1007173173023002624/kGsVT0HP_normal.jpg", "profile_sidebar_fill_color": "FFFFFF", "profile_text_color": "333333", "followers_count": 91392, "profile_sidebar_border_color": "000000", "id_str": "45522363", "profile_background_color": "FFFFFF", "listed_count": 1041, "profile_background_image_url_https": "https://abs.twimg.com/images/themes/theme1/bg.png", "utc_offset": null, "statuses_count": 105234, "description": "#RepsolTeam #EquipoRepsol #MotoGP \ud83d\udc49 #MM93 y #DP26 #Moto3 \ud83d\udc49 Ar\u00f3n Canet y Alonso L\u00f3pez  #Trial \ud83d\udc49 Toni Bou y Fujinami #FIMCEVRepsol #MonlauRepsol", "friends_count": 837, "location": null, "profile_link_color": "FF691F", "profile_image_url": "http://pbs.twimg.com/profile_images/1007173173023002624/kGsVT0HP_normal.jpg", "following": null, "geo_enabled": false, "profile_banner_url": "https://pbs.twimg.com/profile_banners/45522363/1532932490", "profile_background_image_url": "http://abs.twimg.com/images/themes/theme1/bg.png", "name": "Box_Repsol", "lang": "es", "profile_background_tile": false, "favourites_count": 9501, "screen_name": "box_repsol", "notifications": null, "url": "http://www.boxrepsol.com", "created_at": "Mon Jun 08 07:50:23 +0000 2009", "contributors_enabled": false, "time_zone": null, "protected": false, "translator_type": "none", "is_translator": false}, "geo": null, "in_reply_to_user_id_str": null, "possibly_sensitive": false, "lang": "cs", "extended_tweet": {"display_text_range": [0, 196], "entities": {"user_mentions": [], "symbols": [], "hashtags": [{"indices": [0, 5], "text": "MM93"}, {"indices": [6, 14], "text": "CzechGP"}, {"indices": [30, 36], "text": "Moto2"}, {"indices": [65, 72], "text": "MotoGP"}, {"indices": [153, 166], "text": "EquipoRepsol"}, {"indices": [167, 178], "text": "RepsolTeam"}, {"indices": [179, 196], "text": "WheelieWednesday"}], "urls": [], "media": [{"expanded_url": "https://twitter.com/box_repsol/status/1024567741813010432/photo/1", "display_url": "pic.twitter.com/jq2eVKl3dL", "url": "https://t.co/jq2eVKl3dL", "media_url_https": "https://pbs.twimg.com/media/Djf84BxXgAETmqL.jpg", "id_str": "1024565479728447489", "sizes": {"large": {"h": 1365, "resize": "fit", "w": 2048}, "small": {"h": 453, "resize": "fit", "w": 680}, "medium": {"h": 800, "resize": "fit", "w": 1200}, "thumb": {"h": 150, "resize": "crop", "w": 150}}, "indices": [197, 220], "type": "photo", "id": 1024565479728447489, "media_url": "http://pbs.twimg.com/media/Djf84BxXgAETmqL.jpg"}]}, "extended_entities": {"media": [{"expanded_url": "https://twitter.com/box_repsol/status/1024567741813010432/photo/1", "display_url": "pic.twitter.com/jq2eVKl3dL", "url": "https://t.co/jq2eVKl3dL", "media_url_https": "https://pbs.twimg.com/media/Djf84BxXgAETmqL.jpg", "id_str": "1024565479728447489", "sizes": {"large": {"h": 1365, "resize": "fit", "w": 2048}, "small": {"h": 453, "resize": "fit", "w": 680}, "medium": {"h": 800, "resize": "fit", "w": 1200}, "thumb": {"h": 150, "resize": "crop", "w": 150}}, "indices": [197, 220], "type": "photo", "id": 1024565479728447489, "media_url": "http://pbs.twimg.com/media/Djf84BxXgAETmqL.jpg"}]}, "full_text": "#MM93 #CzechGP\n2011 \ud83d\udc49 \ud83e\udd48+ Pole #Moto2\n2012 \ud83d\udc49 \ud83c\udfc6\n2013 \ud83d\udc49 \ud83c\udfc6 + VR / FL #MotoGP\n2014 \ud83d\udc49 Pole\n2015 \ud83d\udc49 \ud83e\udd48 + VR/FL\n2016 \ud83d\udc49 \ud83e\udd49+ Pole\n2017 \ud83d\udc49 \ud83c\udfc6 + Pole\n2018 \ud83d\udc49 \ud83d\udcaf\ud83e\udd37\u200d\u2640\ufe0f \u2753 \ud83e\udd37\u200d\u2642\ufe0f\n#EquipoRepsol #RepsolTeam #WheelieWednesday https://t.co/jq2eVKl3dL"}, "created_at": "Wed Aug 01 08:09:19 +0000 2018", "filter_level": "low", "in_reply_to_status_id_str": null, "place": null}, "user": {"follow_request_sent": null, "profile_use_background_image": false, "default_profile_image": false, "id": 168511185, "default_profile": false, "verified": false, "profile_image_url_https": "https://pbs.twimg.com/profile_images/1021256930184925184/immYMRCm_normal.jpg", "profile_sidebar_fill_color": "000000", "profile_text_color": "000000", "followers_count": 162, "profile_sidebar_border_color": "000000", "id_str": "168511185", "profile_background_color": "000000", "listed_count": 3, "profile_background_image_url_https": "https://abs.twimg.com/images/themes/theme13/bg.gif", "utc_offset": null, "statuses_count": 37606, "description": "\ud83c\udfb9Tor+ Saksit  \ud83c\udfbcCNBLUE * \uac15\ubbfc\ud601 *  \u0e40\u0e1b\u0e25\u0e35\u0e48\u0e22\u0e19\u0e40\u0e21\u0e19\u0e15\u0e32\u0e21\u0e2d\u0e32\u0e23\u0e21\u0e22\u0e4c \u0e22\u0e07-\u0e08\u0e07-\u0e21\u0e34\u0e19-\u0e0a\u0e34\u0e19\ud83c\udfc6\uc774\ub300\ud6c8 \ud83c\uddeb\ud83c\uddf7Marc M\u00e1rquez \ud83d\udd7aSF9*\uac15\ucc2c\ud76c* \ud83d\udc0f\u0e2b\u0e22\u0e32\u0e07\u0e2b\u0e22\u0e32\u0e07", "friends_count": 345, "location": "Thailand", "profile_link_color": "1B95E0", "profile_image_url": "http://pbs.twimg.com/profile_images/1021256930184925184/immYMRCm_normal.jpg", "following": null, "geo_enabled": true, "profile_banner_url": "https://pbs.twimg.com/profile_banners/168511185/1460341377", "profile_background_image_url": "http://abs.twimg.com/images/themes/theme13/bg.gif", "name": "\ud83d\udc99Bumme\ud83d\udc99", "lang": "th", "profile_background_tile": false, "favourites_count": 2359, "screen_name": "bumme_", "notifications": null, "url": null, "created_at": "Mon Jul 19 15:01:42 +0000 2010", "contributors_enabled": false, "time_zone": null, "protected": false, "translator_type": "none", "is_translator": false}, "geo": null, "in_reply_to_user_id_str": null, "lang": "cs", "created_at": "Wed Aug 01 08:15:39 +0000 2018", "filter_level": "low", "in_reply_to_status_id_str": null, "place": null}
{"quote_count": 0, "contributors": null, "truncated": false, "text": "RT @box_repsol: #MM93 #CzechGP\n2011 \ud83d\udc49 \ud83e\udd48+ Pole #Moto2\n2012 \ud83d\udc49 \ud83c\udfc6\n2013 \ud83d\udc49 \ud83c\udfc6 + VR / FL #MotoGP\n2014 \ud83d\udc49 Pole\n2015 \ud83d\udc49 \ud83e\udd48 + VR/FL\n2016 \ud83d\udc49 \ud83e\udd49+ Pole\n2017 \ud83d\udc49\u2026", "is_quote_status": false, "in_reply_to_status_id": null, "reply_count": 0, "id": 1024569358700302336, "favorite_count": 0, "entities": {"user_mentions": [{"id": 45522363, "indices": [3, 14], "id_str": "45522363", "screen_name": "box_repsol", "name": "Box_Repsol"}], "symbols": [], "hashtags": [{"indices": [16, 21], "text": "MM93"}, {"indices": [22, 30], "text": "CzechGP"}, {"indices": [46, 52], "text": "Moto2"}, {"indices": [81, 88], "text": "MotoGP"}], "urls": []}, "retweeted": false, "coordinates": null, "timestamp_ms": "1533111345349", "source": "<a href=\"http://twitter.com/download/android\" rel=\"nofollow\">Twitter for Android</a>", "in_reply_to_screen_name": null, "id_str": "1024569358700302336", "retweet_count": 0, "in_reply_to_user_id": null, "favorited": false, "retweeted_status": {"quote_count": 0, "contributors": null, "truncated": true, "text": "#MM93 #CzechGP\n2011 \ud83d\udc49 \ud83e\udd48+ Pole #Moto2\n2012 \ud83d\udc49 \ud83c\udfc6\n2013 \ud83d\udc49 \ud83c\udfc6 + VR / FL #MotoGP\n2014 \ud83d\udc49 Pole\n2015 \ud83d\udc49 \ud83e\udd48 + VR/FL\n2016 \ud83d\udc49 \ud83e\udd49+ Pol\u2026 https://t.co/iaG3WkTYdn", "is_quote_status": false, "in_reply_to_status_id": null, "reply_count": 0, "id": 1024567741813010432, "favorite_count": 10, "entities": {"user_mentions": [], "symbols": [], "hashtags": [{"indices": [0, 5], "text": "MM93"}, {"indices": [6, 14], "text": "CzechGP"}, {"indices": [30, 36], "text": "Moto2"}, {"indices": [65, 72], "text": "MotoGP"}], "urls": [{"url": "https://t.co/iaG3WkTYdn", "indices": [117, 140], "expanded_url": "https://twitter.com/i/web/status/1024567741813010432", "display_url": "twitter.com/i/web/status/1\u2026"}]}, "retweeted": false, "coordinates": null, "source": "<a href=\"http://twitter.com\" rel=\"nofollow\">Twitter Web Client</a>", "in_reply_to_screen_name": null, "id_str": "1024567741813010432", "display_text_range": [0, 140], "retweet_count": 7, "in_reply_to_user_id": null, "favorited": false, "user": {"follow_request_sent": null, "profile_use_background_image": true, "default_profile_image": false, "id": 45522363, "default_profile": false, "verified": true, "profile_image_url_https": "https://pbs.twimg.com/profile_images/1007173173023002624/kGsVT0HP_normal.jpg", "profile_sidebar_fill_color": "FFFFFF", "profile_text_color": "333333", "followers_count": 91392, "profile_sidebar_border_color": "000000", "id_str": "45522363", "profile_background_color": "FFFFFF", "listed_count": 1041, "profile_background_image_url_https": "https://abs.twimg.com/images/themes/theme1/bg.png", "utc_offset": null, "statuses_count": 105234, "description": "#RepsolTeam #EquipoRepsol #MotoGP \ud83d\udc49 #MM93 y #DP26 #Moto3 \ud83d\udc49 Ar\u00f3n Canet y Alonso L\u00f3pez  #Trial \ud83d\udc49 Toni Bou y Fujinami #FIMCEVRepsol #MonlauRepsol", "friends_count": 837, "location": null, "profile_link_color": "FF691F", "profile_image_url": "http://pbs.twimg.com/profile_images/1007173173023002624/kGsVT0HP_normal.jpg", "following": null, "geo_enabled": false, "profile_banner_url": "https://pbs.twimg.com/profile_banners/45522363/1532932490", "profile_background_image_url": "http://abs.twimg.com/images/themes/theme1/bg.png", "name": "Box_Repsol", "lang": "es", "profile_background_tile": false, "favourites_count": 9501, "screen_name": "box_repsol", "notifications": null, "url": "http://www.boxrepsol.com", "created_at": "Mon Jun 08 07:50:23 +0000 2009", "contributors_enabled": false, "time_zone": null, "protected": false, "translator_type": "none", "is_translator": false}, "geo": null, "in_reply_to_user_id_str": null, "possibly_sensitive": false, "lang": "cs", "extended_tweet": {"display_text_range": [0, 196], "entities": {"user_mentions": [], "symbols": [], "hashtags": [{"indices": [0, 5], "text": "MM93"}, {"indices": [6, 14], "text": "CzechGP"}, {"indices": [30, 36], "text": "Moto2"}, {"indices": [65, 72], "text": "MotoGP"}, {"indices": [153, 166], "text": "EquipoRepsol"}, {"indices": [167, 178], "text": "RepsolTeam"}, {"indices": [179, 196], "text": "WheelieWednesday"}], "urls": [], "media": [{"expanded_url": "https://twitter.com/box_repsol/status/1024567741813010432/photo/1", "display_url": "pic.twitter.com/jq2eVKl3dL", "url": "https://t.co/jq2eVKl3dL", "media_url_https": "https://pbs.twimg.com/media/Djf84BxXgAETmqL.jpg", "id_str": "1024565479728447489", "sizes": {"large": {"h": 1365, "resize": "fit", "w": 2048}, "small": {"h": 453, "resize": "fit", "w": 680}, "medium": {"h": 800, "resize": "fit", "w": 1200}, "thumb": {"h": 150, "resize": "crop", "w": 150}}, "indices": [197, 220], "type": "photo", "id": 1024565479728447489, "media_url": "http://pbs.twimg.com/media/Djf84BxXgAETmqL.jpg"}]}, "extended_entities": {"media": [{"expanded_url": "https://twitter.com/box_repsol/status/1024567741813010432/photo/1", "display_url": "pic.twitter.com/jq2eVKl3dL", "url": "https://t.co/jq2eVKl3dL", "media_url_https": "https://pbs.twimg.com/media/Djf84BxXgAETmqL.jpg", "id_str": "1024565479728447489", "sizes": {"large": {"h": 1365, "resize": "fit", "w": 2048}, "small": {"h": 453, "resize": "fit", "w": 680}, "medium": {"h": 800, "resize": "fit", "w": 1200}, "thumb": {"h": 150, "resize": "crop", "w": 150}}, "indices": [197, 220], "type": "photo", "id": 1024565479728447489, "media_url": "http://pbs.twimg.com/media/Djf84BxXgAETmqL.jpg"}]}, "full_text": "#MM93 #CzechGP\n2011 \ud83d\udc49 \ud83e\udd48+ Pole #Moto2\n2012 \ud83d\udc49 \ud83c\udfc6\n2013 \ud83d\udc49 \ud83c\udfc6 + VR / FL #MotoGP\n2014 \ud83d\udc49 Pole\n2015 \ud83d\udc49 \ud83e\udd48 + VR/FL\n2016 \ud83d\udc49 \ud83e\udd49+ Pole\n2017 \ud83d\udc49 \ud83c\udfc6 + Pole\n2018 \ud83d\udc49 \ud83d\udcaf\ud83e\udd37\u200d\u2640\ufe0f \u2753 \ud83e\udd37\u200d\u2642\ufe0f\n#EquipoRepsol #RepsolTeam #WheelieWednesday https://t.co/jq2eVKl3dL"}, "created_at": "Wed Aug 01 08:09:19 +0000 2018", "filter_level": "low", "in_reply_to_status_id_str": null, "place": null}, "user": {"follow_request_sent": null, "profile_use_background_image": true, "default_profile_image": false, "id": 923225196, "default_profile": false, "verified": false, "profile_image_url_https": "https://pbs.twimg.com/profile_images/1013752048678944768/nc7q7TJa_normal.jpg", "profile_sidebar_fill_color": "99CC33", "profile_text_color": "3E4415", "followers_count": 1370, "profile_sidebar_border_color": "829D5E", "id_str": "923225196", "profile_background_color": "352726", "listed_count": 82, "profile_background_image_url_https": "https://abs.twimg.com/images/themes/theme5/bg.gif", "utc_offset": null, "statuses_count": 371819, "description": "@agnezmo \u2022 @zaynmalik :) || OTRA Indo + Zayn leaving 1D 25/03/15 \ud83d\ude27 || -MOM- 25/03/16 || -X- 10/10/17 #Zquad #AGnation", "friends_count": 682, "location": null, "profile_link_color": "D02B55", "profile_image_url": "http://pbs.twimg.com/profile_images/1013752048678944768/nc7q7TJa_normal.jpg", "following": null, "geo_enabled": true, "profile_banner_url": "https://pbs.twimg.com/profile_banners/923225196/1530532294", "profile_background_image_url": "http://abs.twimg.com/images/themes/theme5/bg.gif", "name": "Overdose OUT NOW!!", "lang": "id", "profile_background_tile": false, "favourites_count": 8933, "screen_name": "Yzahra93", "notifications": null, "url": "https://open.spotify.com/track/2jzFNGqC0Q1TeThJTzPL0T?si=CXgh8fTXQticbpaq1_p8Eg", "created_at": "Sat Nov 03 13:35:46 +0000 2012", "contributors_enabled": false, "time_zone": null, "protected": false, "translator_type": "none", "is_translator": false}, "geo": null, "in_reply_to_user_id_str": null, "lang": "cs", "created_at": "Wed Aug 01 08:15:45 +0000 2018", "filter_level": "low", "in_reply_to_status_id_str": null, "place": null}
