{"quote_count": 0, "contributors": null, "truncated": false, "text": "RT @MotoGP: Rossi closes in on 6000 Grand Prix points \ud83c\udfc1\n\nThe Italian could make history at the #CzechGP by becoming the first rider to scor\u2026", "is_quote_status": false, "in_reply_to_status_id": null, "reply_count": 0, "id": 1024543498287108098, "favorite_count": 0, "entities": {"user_mentions": [{"id": 14082692, "indices": [3, 10], "id_str": "14082692", "screen_name": "MotoGP", "name": "MotoGP\u2122\ud83c\udde8\ud83c\uddff\ud83c\udfc1"}], "symbols": [], "hashtags": [{"indices": [95, 103], "text": "CzechGP"}], "urls": []}, "retweeted": false, "coordinates": null, "timestamp_ms": "1533105179746", "source": "<a href=\"http://twitter.com/download/android\" rel=\"nofollow\">Twitter for Android</a>", "in_reply_to_screen_name": null, "id_str": "1024543498287108098", "retweet_count": 0, "in_reply_to_user_id": null, "favorited": false, "retweeted_status": {"quote_count": 15, "contributors": null, "truncated": true, "text": "Rossi closes in on 6000 Grand Prix points \ud83c\udfc1\n\nThe Italian could make history at the #CzechGP by becoming the first r\u2026 https://t.co/Am6SKnn23l", "is_quote_status": false, "in_reply_to_status_id": null, "reply_count": 11, "id": 1024318770360270848, "favorite_count": 683, "entities": {"user_mentions": [], "symbols": [], "hashtags": [{"indices": [83, 91], "text": "CzechGP"}], "urls": [{"url": "https://t.co/Am6SKnn23l", "indices": [117, 140], "expanded_url": "https://twitter.com/i/web/status/1024318770360270848", "display_url": "twitter.com/i/web/status/1\u2026"}]}, "retweeted": false, "coordinates": null, "source": "<a href=\"https://about.twitter.com/products/tweetdeck\" rel=\"nofollow\">TweetDeck</a>", "in_reply_to_screen_name": null, "id_str": "1024318770360270848", "display_text_range": [0, 140], "retweet_count": 221, "in_reply_to_user_id": null, "favorited": false, "user": {"follow_request_sent": null, "profile_use_background_image": true, "default_profile_image": false, "id": 14082692, "default_profile": false, "verified": true, "profile_image_url_https": "https://pbs.twimg.com/profile_images/466637052885217280/sVktQhxZ_normal.png", "profile_sidebar_fill_color": "DEDEDE", "profile_text_color": "262626", "followers_count": 2434119, "profile_sidebar_border_color": "FFFFFF", "id_str": "14082692", "profile_background_color": "000000", "listed_count": 10142, "profile_background_image_url_https": "https://abs.twimg.com/images/themes/theme1/bg.png", "utc_offset": null, "statuses_count": 50930, "description": "First on the throttle, last on the brakes.", "friends_count": 286, "location": "The World", "profile_link_color": "ED134D", "profile_image_url": "http://pbs.twimg.com/profile_images/466637052885217280/sVktQhxZ_normal.png", "following": null, "geo_enabled": false, "profile_banner_url": "https://pbs.twimg.com/profile_banners/14082692/1533038792", "profile_background_image_url": "http://abs.twimg.com/images/themes/theme1/bg.png", "name": "MotoGP\u2122\ud83c\udde8\ud83c\uddff\ud83c\udfc1", "lang": "en", "profile_background_tile": false, "favourites_count": 5990, "screen_name": "MotoGP", "notifications": null, "url": "http://www.motogp.com", "created_at": "Wed Mar 05 11:19:05 +0000 2008", "contributors_enabled": false, "time_zone": null, "protected": false, "translator_type": "none", "is_translator": false}, "geo": null, "in_reply_to_user_id_str": null, "possibly_sensitive": false, "lang": "en", "extended_tweet": {"display_text_range": [0, 178], "entities": {"user_mentions": [], "symbols": [], "hashtags": [{"indices": [83, 91], "text": "CzechGP"}, {"indices": [143, 150], "text": "MotoGP"}], "urls": [{"url": "https://t.co/6sF7IcBW8o", "indices": [155, 178], "expanded_url": "http://www.motogp.com/en/news/2018/07/31/rossi-closes-in-on-6000-grand-prix-points/266146", "display_url": "motogp.com/en/news/2018/0\u2026"}], "media": [{"expanded_url": "https://twitter.com/MotoGP/status/1024318770360270848/photo/1", "display_url": "pic.twitter.com/udhvAaflGu", "url": "https://t.co/udhvAaflGu", "media_url_https": "https://pbs.twimg.com/media/DjcDOwDXcAECnDh.jpg", "id_str": "1024290992202149889", "sizes": {"large": {"h": 951, "resize": "fit", "w": 1200}, "small": {"h": 539, "resize": "fit", "w": 680}, "medium": {"h": 951, "resize": "fit", "w": 1200}, "thumb": {"h": 150, "resize": "crop", "w": 150}}, "indices": [179, 202], "type": "photo", "id": 1024290992202149889, "media_url": "http://pbs.twimg.com/media/DjcDOwDXcAECnDh.jpg"}]}, "extended_entities": {"media": [{"expanded_url": "https://twitter.com/MotoGP/status/1024318770360270848/photo/1", "display_url": "pic.twitter.com/udhvAaflGu", "url": "https://t.co/udhvAaflGu", "media_url_https": "https://pbs.twimg.com/media/DjcDOwDXcAECnDh.jpg", "id_str": "1024290992202149889", "sizes": {"large": {"h": 951, "resize": "fit", "w": 1200}, "small": {"h": 539, "resize": "fit", "w": 680}, "medium": {"h": 951, "resize": "fit", "w": 1200}, "thumb": {"h": 150, "resize": "crop", "w": 150}}, "indices": [179, 202], "type": "photo", "id": 1024290992202149889, "media_url": "http://pbs.twimg.com/media/DjcDOwDXcAECnDh.jpg"}]}, "full_text": "Rossi closes in on 6000 Grand Prix points \ud83c\udfc1\n\nThe Italian could make history at the #CzechGP by becoming the first rider to score 6000 points \n\n#MotoGP | \ud83d\udcf0 https://t.co/6sF7IcBW8o https://t.co/udhvAaflGu"}, "created_at": "Tue Jul 31 15:40:00 +0000 2018", "filter_level": "low", "in_reply_to_status_id_str": null, "place": null}, "user": {"follow_request_sent": null, "profile_use_background_image": true, "default_profile_image": false, "id": 747569905235537920, "default_profile": true, "verified": false, "profile_image_url_https": "https://pbs.twimg.com/profile_images/1010965718299488257/WaW-42E-_normal.jpg", "profile_sidebar_fill_color": "DDEEF6", "profile_text_color": "333333", "followers_count": 3611, "profile_sidebar_border_color": "C0DEED", "id_str": "747569905235537920", "profile_background_color": "F5F8FA", "listed_count": 5, "profile_background_image_url_https": "", "utc_offset": null, "statuses_count": 43566, "description": "God Is Great \ud83d\ude4f", "friends_count": 3005, "location": "Port Harcourt, Nigeria", "profile_link_color": "1DA1F2", "profile_image_url": "http://pbs.twimg.com/profile_images/1010965718299488257/WaW-42E-_normal.jpg", "following": null, "geo_enabled": false, "profile_banner_url": "https://pbs.twimg.com/profile_banners/747569905235537920/1530192283", "profile_background_image_url": "", "name": "Spirit\ud83d\udc7b", "lang": "en", "profile_background_tile": false, "favourites_count": 54654, "screen_name": "munachimosademe", "notifications": null, "url": null, "created_at": "Mon Jun 27 23:18:49 +0000 2016", "contributors_enabled": false, "time_zone": null, "protected": false, "translator_type": "none", "is_translator": false}, "geo": null, "in_reply_to_user_id_str": null, "lang": "en", "created_at": "Wed Aug 01 06:32:59 +0000 2018", "filter_level": "low", "in_reply_to_status_id_str": null, "place": null}
